azure/mgmt/azureadb2c/__init__.py
azure/mgmt/azureadb2c/_configuration.py
azure/mgmt/azureadb2c/_cpim_configuration_client.py
azure/mgmt/azureadb2c/_version.py
azure/mgmt/azureadb2c/models.py
azure/mgmt/azureadb2c/aio/__init__.py
azure/mgmt/azureadb2c/aio/_configuration.py
azure/mgmt/azureadb2c/aio/_cpim_configuration_client.py
azure/mgmt/azureadb2c/v2019_01_01_preview/__init__.py
azure/mgmt/azureadb2c/v2019_01_01_preview/_configuration.py
azure/mgmt/azureadb2c/v2019_01_01_preview/_cpim_configuration_client.py
azure/mgmt/azureadb2c/v2019_01_01_preview/aio/__init__.py
azure/mgmt/azureadb2c/v2019_01_01_preview/aio/_configuration.py
azure/mgmt/azureadb2c/v2019_01_01_preview/aio/_cpim_configuration_client.py
azure/mgmt/azureadb2c/v2019_01_01_preview/aio/operations/__init__.py
azure/mgmt/azureadb2c/v2019_01_01_preview/aio/operations/_b2_ctenants_operations.py
azure/mgmt/azureadb2c/v2019_01_01_preview/aio/operations/_operations.py
azure/mgmt/azureadb2c/v2019_01_01_preview/models/__init__.py
azure/mgmt/azureadb2c/v2019_01_01_preview/models/_cpim_configuration_client_enums.py
azure/mgmt/azureadb2c/v2019_01_01_preview/models/_models.py
azure/mgmt/azureadb2c/v2019_01_01_preview/models/_models_py3.py
azure/mgmt/azureadb2c/v2019_01_01_preview/operations/__init__.py
azure/mgmt/azureadb2c/v2019_01_01_preview/operations/_b2_ctenants_operations.py
azure/mgmt/azureadb2c/v2019_01_01_preview/operations/_operations.py
azure/mgmt/azureadb2c/v2020_05_01_preview/__init__.py
azure/mgmt/azureadb2c/v2020_05_01_preview/_configuration.py
azure/mgmt/azureadb2c/v2020_05_01_preview/_cpim_configuration_client.py
azure/mgmt/azureadb2c/v2020_05_01_preview/aio/__init__.py
azure/mgmt/azureadb2c/v2020_05_01_preview/aio/_configuration.py
azure/mgmt/azureadb2c/v2020_05_01_preview/aio/_cpim_configuration_client.py
azure/mgmt/azureadb2c/v2020_05_01_preview/aio/operations/__init__.py
azure/mgmt/azureadb2c/v2020_05_01_preview/aio/operations/_guest_usages_operations.py
azure_mgmt_azureadb2c-1.0.0b2.dist-info/LICENSE
azure_mgmt_azureadb2c-1.0.0b2.dist-info/METADATA
azure_mgmt_azureadb2c-1.0.0b2.dist-info/WHEEL
azure_mgmt_azureadb2c-1.0.0b2.dist-info/top_level.txt
azure_mgmt_azureadb2c-1.0.0b2.dist-info/RECORD
